iota_exrate_manager/__init__.py
iota_exrate_manager/apis.py
iota_exrate_manager/utils.py
iota_exrate_manager-0.1.2.dist-info/LICENSE
iota_exrate_manager-0.1.2.dist-info/METADATA
iota_exrate_manager-0.1.2.dist-info/WHEEL
iota_exrate_manager-0.1.2.dist-info/top_level.txt
iota_exrate_manager-0.1.2.dist-info/RECORD
